megarest/__init__.py
megarest/__main__.py
megarest/api.py
megarest/app.py
megarest/device.py
megarest/pin.py
megarest/pushbutton.py
megarest/stepper.py
megarest-0.0.4.dist-info/DESCRIPTION.rst
megarest-0.0.4.dist-info/METADATA
megarest-0.0.4.dist-info/RECORD
megarest-0.0.4.dist-info/WHEEL
megarest-0.0.4.dist-info/metadata.json
megarest-0.0.4.dist-info/top_level.txt
